availai/__init__.py
availai/datasets/__init__.py
availai/datasets/dataset.py
availai/experiments/__init__.py
availai/experiments/experiment.py
availai/training/__init__.py
tests/__init__.py
tests/datasets/__init__.py
tests/datasets/downloading_from_roboflow.py
availai-0.5.0.dist-info/LICENSE
availai-0.5.0.dist-info/METADATA
availai-0.5.0.dist-info/WHEEL
availai-0.5.0.dist-info/top_level.txt
availai-0.5.0.dist-info/RECORD
